comfyui_workflow_templates/__init__.py
comfyui_workflow_templates-0.8.1.dist-info/licenses/LICENSE
comfyui_workflow_templates-0.8.1.dist-info/METADATA
comfyui_workflow_templates-0.8.1.dist-info/WHEEL
comfyui_workflow_templates-0.8.1.dist-info/top_level.txt
comfyui_workflow_templates-0.8.1.dist-info/RECORD
