Metadata-Version: 2.4
Name: comfyui_workflow_templates
Version: 0.8.1
Summary: ComfyUI workflow templates package
Author: Comfy-Org
License: MIT
Classifier: Programming Language :: Python :: 3
Classifier: Operating System :: OS Independent
Requires-Python: >=3.9
License-File: LICENSE
Requires-Dist: comfyui-workflow-templates-core==0.3.85
Requires-Dist: comfyui-workflow-templates-media-api==0.3.38
Requires-Dist: comfyui-workflow-templates-media-video==0.3.37
Requires-Dist: comfyui-workflow-templates-media-image==0.3.54
Requires-Dist: comfyui-workflow-templates-media-other==0.3.76
Provides-Extra: api
Requires-Dist: comfyui-workflow-templates-media-api==0.3.38; extra == "api"
Provides-Extra: video
Requires-Dist: comfyui-workflow-templates-media-video==0.3.37; extra == "video"
Provides-Extra: image
Requires-Dist: comfyui-workflow-templates-media-image==0.3.54; extra == "image"
Provides-Extra: other
Requires-Dist: comfyui-workflow-templates-media-other==0.3.76; extra == "other"
Provides-Extra: all
Requires-Dist: comfyui-workflow-templates-media-api==0.3.38; extra == "all"
Requires-Dist: comfyui-workflow-templates-media-video==0.3.37; extra == "all"
Requires-Dist: comfyui-workflow-templates-media-image==0.3.54; extra == "all"
Requires-Dist: comfyui-workflow-templates-media-other==0.3.76; extra == "all"
Dynamic: license-file
